test/__init__.py
test/test_zia.py
zscalertools/__init__.py
zscalertools/zia.py
zscalertools-0.0.11.dist-info/LICENSE
zscalertools-0.0.11.dist-info/METADATA
zscalertools-0.0.11.dist-info/WHEEL
zscalertools-0.0.11.dist-info/top_level.txt
zscalertools-0.0.11.dist-info/RECORD
