Metadata-Version: 2.1
Name: zscalertools
Version: 0.0.11
Summary: Zscaler Tools
Home-page: https://github.mmm.com/network-automation/zscalertools
Author: Bryce Myers
Author-email: bdmyers@mmm.com
License: UNKNOWN
Platform: UNKNOWN
Classifier: Programming Language :: Python :: 3
Classifier: License :: OSI Approved :: MIT License
Classifier: Operating System :: OS Independent
Requires-Python: >=3.6
Requires-Dist: requests
